{"nodes": [{"id": "processorder", "label": "ProcessOrder.ps1", "file_type": "code", "source_file": "example\\TC_AI_DOTNET_Samples\\src\\ScriptingContainer\\CodeGenerationDemo\\ProcessOrder.ps1", "source_location": "L1"}, {"id": "processorder_main", "label": "main()", "file_type": "code", "source_file": "example\\TC_AI_DOTNET_Samples\\src\\ScriptingContainer\\CodeGenerationDemo\\ProcessOrder.ps1", "source_location": "L27"}, {"id": "processorder_process_order", "label": "Process-Order()", "file_type": "code", "source_file": "example\\TC_AI_DOTNET_Samples\\src\\ScriptingContainer\\CodeGenerationDemo\\ProcessOrder.ps1", "source_location": "L101"}, {"id": "processorder_get_scriptdirectory", "label": "Get-ScriptDirectory()", "file_type": "code", "source_file": "example\\TC_AI_DOTNET_Samples\\src\\ScriptingContainer\\CodeGenerationDemo\\ProcessOrder.ps1", "source_location": "L192"}, {"id": "processorder_create_hardware", "label": "Create-Hardware()", "file_type": "code", "source_file": "example\\TC_AI_DOTNET_Samples\\src\\ScriptingContainer\\CodeGenerationDemo\\ProcessOrder.ps1", "source_location": "L209"}, {"id": "processorder_count_boxes", "label": "Count-Boxes()", "file_type": "code", "source_file": "example\\TC_AI_DOTNET_Samples\\src\\ScriptingContainer\\CodeGenerationDemo\\ProcessOrder.ps1", "source_location": "L299"}, {"id": "processorder_create_box", "label": "Create-Box()", "file_type": "code", "source_file": "example\\TC_AI_DOTNET_Samples\\src\\ScriptingContainer\\CodeGenerationDemo\\ProcessOrder.ps1", "source_location": "L320"}, {"id": "processorder_create_plcproject", "label": "Create-PlcProject()", "file_type": "code", "source_file": "example\\TC_AI_DOTNET_Samples\\src\\ScriptingContainer\\CodeGenerationDemo\\ProcessOrder.ps1", "source_location": "L365"}, {"id": "processorder_create_worksheet", "label": "Create-Worksheet()", "file_type": "code", "source_file": "example\\TC_AI_DOTNET_Samples\\src\\ScriptingContainer\\CodeGenerationDemo\\ProcessOrder.ps1", "source_location": "L486"}, {"id": "processorder_create_motion", "label": "Create-Motion()", "file_type": "code", "source_file": "example\\TC_AI_DOTNET_Samples\\src\\ScriptingContainer\\CodeGenerationDemo\\ProcessOrder.ps1", "source_location": "L552"}, {"id": "processorder_create_mappings", "label": "Create-Mappings()", "file_type": "code", "source_file": "example\\TC_AI_DOTNET_Samples\\src\\ScriptingContainer\\CodeGenerationDemo\\ProcessOrder.ps1", "source_location": "L638"}, {"id": "processorder_create_scope", "label": "Create-Scope()", "file_type": "code", "source_file": "example\\TC_AI_DOTNET_Samples\\src\\ScriptingContainer\\CodeGenerationDemo\\ProcessOrder.ps1", "source_location": "L668"}, {"id": "processorder_create_chart", "label": "Create-Chart()", "file_type": "code", "source_file": "example\\TC_AI_DOTNET_Samples\\src\\ScriptingContainer\\CodeGenerationDemo\\ProcessOrder.ps1", "source_location": "L722"}], "edges": [{"source": "processorder", "target": "processorder_main", "relation": "contains", "confidence": "EXTRACTED", "source_file": "example\\TC_AI_DOTNET_Samples\\src\\ScriptingContainer\\CodeGenerationDemo\\ProcessOrder.ps1", "source_location": "L27", "weight": 1.0}, {"source": "processorder", "target": "processorder_process_order", "relation": "contains", "confidence": "EXTRACTED", "source_file": "example\\TC_AI_DOTNET_Samples\\src\\ScriptingContainer\\CodeGenerationDemo\\ProcessOrder.ps1", "source_location": "L101", "weight": 1.0}, {"source": "processorder", "target": "processorder_get_scriptdirectory", "relation": "contains", "confidence": "EXTRACTED", "source_file": "example\\TC_AI_DOTNET_Samples\\src\\ScriptingContainer\\CodeGenerationDemo\\ProcessOrder.ps1", "source_location": "L192", "weight": 1.0}, {"source": "processorder", "target": "processorder_create_hardware", "relation": "contains", "confidence": "EXTRACTED", "source_file": "example\\TC_AI_DOTNET_Samples\\src\\ScriptingContainer\\CodeGenerationDemo\\ProcessOrder.ps1", "source_location": "L209", "weight": 1.0}, {"source": "processorder", "target": "processorder_count_boxes", "relation": "contains", "confidence": "EXTRACTED", "source_file": "example\\TC_AI_DOTNET_Samples\\src\\ScriptingContainer\\CodeGenerationDemo\\ProcessOrder.ps1", "source_location": "L299", "weight": 1.0}, {"source": "processorder", "target": "processorder_create_box", "relation": "contains", "confidence": "EXTRACTED", "source_file": "example\\TC_AI_DOTNET_Samples\\src\\ScriptingContainer\\CodeGenerationDemo\\ProcessOrder.ps1", "source_location": "L320", "weight": 1.0}, {"source": "processorder", "target": "processorder_create_plcproject", "relation": "contains", "confidence": "EXTRACTED", "source_file": "example\\TC_AI_DOTNET_Samples\\src\\ScriptingContainer\\CodeGenerationDemo\\ProcessOrder.ps1", "source_location": "L365", "weight": 1.0}, {"source": "processorder", "target": "processorder_create_worksheet", "relation": "contains", "confidence": "EXTRACTED", "source_file": "example\\TC_AI_DOTNET_Samples\\src\\ScriptingContainer\\CodeGenerationDemo\\ProcessOrder.ps1", "source_location": "L486", "weight": 1.0}, {"source": "processorder", "target": "processorder_create_motion", "relation": "contains", "confidence": "EXTRACTED", "source_file": "example\\TC_AI_DOTNET_Samples\\src\\ScriptingContainer\\CodeGenerationDemo\\ProcessOrder.ps1", "source_location": "L552", "weight": 1.0}, {"source": "processorder", "target": "processorder_create_mappings", "relation": "contains", "confidence": "EXTRACTED", "source_file": "example\\TC_AI_DOTNET_Samples\\src\\ScriptingContainer\\CodeGenerationDemo\\ProcessOrder.ps1", "source_location": "L638", "weight": 1.0}, {"source": "processorder", "target": "processorder_create_scope", "relation": "contains", "confidence": "EXTRACTED", "source_file": "example\\TC_AI_DOTNET_Samples\\src\\ScriptingContainer\\CodeGenerationDemo\\ProcessOrder.ps1", "source_location": "L668", "weight": 1.0}, {"source": "processorder", "target": "processorder_create_chart", "relation": "contains", "confidence": "EXTRACTED", "source_file": "example\\TC_AI_DOTNET_Samples\\src\\ScriptingContainer\\CodeGenerationDemo\\ProcessOrder.ps1", "source_location": "L722", "weight": 1.0}, {"source": "processorder_main", "target": "processorder_get_scriptdirectory", "relation": "calls", "confidence": "INFERRED", "source_file": "example\\TC_AI_DOTNET_Samples\\src\\ScriptingContainer\\CodeGenerationDemo\\ProcessOrder.ps1", "source_location": "L42", "weight": 0.8}, {"source": "processorder_main", "target": "processorder_process_order", "relation": "calls", "confidence": "INFERRED", "source_file": "example\\TC_AI_DOTNET_Samples\\src\\ScriptingContainer\\CodeGenerationDemo\\ProcessOrder.ps1", "source_location": "L70", "weight": 0.8}, {"source": "processorder_process_order", "target": "processorder_create_hardware", "relation": "calls", "confidence": "INFERRED", "source_file": "example\\TC_AI_DOTNET_Samples\\src\\ScriptingContainer\\CodeGenerationDemo\\ProcessOrder.ps1", "source_location": "L155", "weight": 0.8}, {"source": "processorder_process_order", "target": "processorder_create_plcproject", "relation": "calls", "confidence": "INFERRED", "source_file": "example\\TC_AI_DOTNET_Samples\\src\\ScriptingContainer\\CodeGenerationDemo\\ProcessOrder.ps1", "source_location": "L162", "weight": 0.8}, {"source": "processorder_process_order", "target": "processorder_create_motion", "relation": "calls", "confidence": "INFERRED", "source_file": "example\\TC_AI_DOTNET_Samples\\src\\ScriptingContainer\\CodeGenerationDemo\\ProcessOrder.ps1", "source_location": "L169", "weight": 0.8}, {"source": "processorder_process_order", "target": "processorder_create_mappings", "relation": "calls", "confidence": "INFERRED", "source_file": "example\\TC_AI_DOTNET_Samples\\src\\ScriptingContainer\\CodeGenerationDemo\\ProcessOrder.ps1", "source_location": "L183", "weight": 0.8}, {"source": "processorder_create_hardware", "target": "processorder_count_boxes", "relation": "calls", "confidence": "INFERRED", "source_file": "example\\TC_AI_DOTNET_Samples\\src\\ScriptingContainer\\CodeGenerationDemo\\ProcessOrder.ps1", "source_location": "L280", "weight": 0.8}, {"source": "processorder_create_hardware", "target": "processorder_create_box", "relation": "calls", "confidence": "INFERRED", "source_file": "example\\TC_AI_DOTNET_Samples\\src\\ScriptingContainer\\CodeGenerationDemo\\ProcessOrder.ps1", "source_location": "L289", "weight": 0.8}, {"source": "processorder_create_plcproject", "target": "processorder_create_worksheet", "relation": "calls", "confidence": "INFERRED", "source_file": "example\\TC_AI_DOTNET_Samples\\src\\ScriptingContainer\\CodeGenerationDemo\\ProcessOrder.ps1", "source_location": "L449", "weight": 0.8}, {"source": "processorder_create_scope", "target": "processorder_create_chart", "relation": "calls", "confidence": "INFERRED", "source_file": "example\\TC_AI_DOTNET_Samples\\src\\ScriptingContainer\\CodeGenerationDemo\\ProcessOrder.ps1", "source_location": "L698", "weight": 0.8}]}